setup.py
empowering/__init__.py
empowering/models.py
empowering/resource.py
empowering/results.py
empowering/service.py
empowering/utils.py
empowering.egg-info/PKG-INFO
empowering.egg-info/SOURCES.txt
empowering.egg-info/dependency_links.txt
empowering.egg-info/not-zip-safe
empowering.egg-info/requires.txt
empowering.egg-info/top_level.txt
empowering/executors/__init__.py
empowering/executors/urllib2_executor.py
test/test_backform.py