Metadata-Version: 1.1
Name: empowering
Version: 0.15.3
Summary: Python library for the Empowering REST API.
Home-page: http://code.gisce.net/empowering
Author: GISCE-TI, S.L.
Author-email: devel@gisce.net
License: MIT
Platform: UNKNOWN
Classifier: Intended Audience :: Developers
Classifier: Operating System :: OS Independent
Classifier: Programming Language :: Python
Classifier: Topic :: Software Development :: Libraries :: Python Modules
